LingmoUIPy/__init__.py
LingmoUIPy/etc/LingmoUI3/version
LingmoUIPy/lib/cmake/LingmoUI3/LingmoUI3Config.cmake
LingmoUIPy/lib/cmake/LingmoUI3/LingmoUI3ConfigVersion.cmake
LingmoUIPy/lib/cmake/LingmoUI3/LingmoUITargets-release.cmake
LingmoUIPy/lib/cmake/LingmoUI3/LingmoUITargets.cmake
LingmoUIPy/qml/LingmoUI/LingmoUI3.dll
LingmoUIPy/qml/LingmoUI/LingmoUI3.exp
LingmoUIPy/qml/LingmoUI/LingmoUI3.lib
LingmoUIPy/qml/LingmoUI/LingmoUI3_qml_module_dir_map.qrc
LingmoUIPy/qml/LingmoUI/plugins.qmltypes
LingmoUIPy/qml/LingmoUI/qmldir
LingmoUIPy/qml/LingmoUI/CompatibleModule/LingmoUI3CompatibleModule.dll
LingmoUIPy/qml/LingmoUI/CompatibleModule/LingmoUI3CompatibleModule.exp
LingmoUIPy/qml/LingmoUI/CompatibleModule/LingmoUI3CompatibleModule.lib
LingmoUIPy/qml/LingmoUI/CompatibleModule/LingmoUI3CompatibleModule_qml_module_dir_map.qrc
LingmoUIPy/qml/LingmoUI/CompatibleModule/plugins.qmltypes
LingmoUIPy/qml/LingmoUI/CompatibleModule/qmldir
LingmoUIPy/qml/LingmoUI/CompatibleModule/Controls/AboutDialog.qml
LingmoUIPy/qml/LingmoUI/CompatibleModule/Controls/ActionTextField.qml
LingmoUIPy/qml/LingmoUI/CompatibleModule/Controls/BusyIndicator.qml
LingmoUIPy/qml/LingmoUI/CompatibleModule/Controls/DesktopMenu.qml
LingmoUIPy/qml/LingmoUI/CompatibleModule/Controls/Dialog.qml
LingmoUIPy/qml/LingmoUI/CompatibleModule/Controls/Icon.qml
LingmoUIPy/qml/LingmoUI/CompatibleModule/Controls/PopupTips.qml
LingmoUIPy/qml/LingmoUI/CompatibleModule/Controls/RoundImageButton.qml
LingmoUIPy/qml/LingmoUI/CompatibleModule/Controls/RoundedRect.qml
LingmoUIPy/qml/LingmoUI/CompatibleModule/Controls/TabBar.qml
LingmoUIPy/qml/LingmoUI/CompatibleModule/Controls/TabButton.qml
LingmoUIPy/qml/LingmoUI/CompatibleModule/Controls/TabCloseButton.qml
LingmoUIPy/qml/LingmoUI/CompatibleModule/Controls/TabView.qml
LingmoUIPy/qml/LingmoUI/CompatibleModule/Controls/TextField.qml
LingmoUIPy/qml/LingmoUI/CompatibleModule/Controls/Theme.qml
LingmoUIPy/qml/LingmoUI/CompatibleModule/Controls/Toast.qml
LingmoUIPy-3.0.dist-info/LICENSE
LingmoUIPy-3.0.dist-info/METADATA
LingmoUIPy-3.0.dist-info/WHEEL
LingmoUIPy-3.0.dist-info/top_level.txt
LingmoUIPy-3.0.dist-info/RECORD
